{
    "<StartNode>k__BackingField": {
        "<NodeId>k__BackingField": {
            "_value": "ec6745a9-5c72-4778-af0f-21cb27df2890"
        },
        "<BackgroundHolder>k__BackingField": {
            "<BackgroundId>k__BackingField": {
                "_value": ""
            }
        },
        "<ActorsHolder>k__BackingField": {
            "rid": 1000
        },
        "<Position>k__BackingField": {
            "x": -28.400001525878908,
            "y": 462.0
        },
        "<NextNode>k__BackingField": {
            "_value": "04bfd59c-6b11-4048-ab85-3709ce94442c"
        }
    },
    "<Nodes>k__BackingField": [
        {
            "rid": 1001
        },
        {
            "rid": 1002
        },
        {
            "rid": 1003
        },
        {
            "rid": 1004
        },
        {
            "rid": 1005
        }
    ],
    "references": {
        "version": 2,
        "RefIds": [
            {
                "rid": 1000,
                "type": {
                    "class": "ActorsHolderData",
                    "ns": "KissMyAssets.VisualNovelCore.Runtime",
                    "asm": "Assembly-CSharp"
                },
                "data": {
                    "<Actors>k__BackingField": []
                }
            },
            {
                "rid": 1001,
                "type": {
                    "class": "DialogueStartNodeData",
                    "ns": "KissMyAssets.VisualNovelCore.Runtime",
                    "asm": "Assembly-CSharp"
                },
                "data": {
                    "<NodeId>k__BackingField": {
                        "_value": "ec6745a9-5c72-4778-af0f-21cb27df2890"
                    },
                    "<BackgroundHolder>k__BackingField": {
                        "<BackgroundId>k__BackingField": {
                            "_value": ""
                        }
                    },
                    "<ActorsHolder>k__BackingField": {
                        "rid": 1000
                    },
                    "<Position>k__BackingField": {
                        "x": -28.400001525878908,
                        "y": 462.0
                    },
                    "<NextNode>k__BackingField": {
                        "_value": "04bfd59c-6b11-4048-ab85-3709ce94442c"
                    }
                }
            },
            {
                "rid": 1002,
                "type": {
                    "class": "DialogueEndNodeData",
                    "ns": "KissMyAssets.VisualNovelCore.Runtime",
                    "asm": "Assembly-CSharp"
                },
                "data": {
                    "<NodeId>k__BackingField": {
                        "_value": "4c330dd9-3755-4e5b-a73b-1044234131b0"
                    },
                    "<BackgroundHolder>k__BackingField": {
                        "<BackgroundId>k__BackingField": {
                            "_value": ""
                        }
                    },
                    "<ActorsHolder>k__BackingField": {
                        "rid": 1006
                    },
                    "<Position>k__BackingField": {
                        "x": 1257.199951171875,
                        "y": 524.4000244140625
                    }
                }
            },
            {
                "rid": 1003,
                "type": {
                    "class": "DialogueReplicaNodeData",
                    "ns": "KissMyAssets.VisualNovelCore.Runtime",
                    "asm": "Assembly-CSharp"
                },
                "data": {
                    "<NodeId>k__BackingField": {
                        "_value": "04bfd59c-6b11-4048-ab85-3709ce94442c"
                    },
                    "<BackgroundHolder>k__BackingField": {
                        "<BackgroundId>k__BackingField": {
                            "_value": "00000000-0000-0000-0000-000000000000"
                        }
                    },
                    "<ActorsHolder>k__BackingField": {
                        "rid": 1007
                    },
                    "<Position>k__BackingField": {
                        "x": 91.59996032714844,
                        "y": 141.1999969482422
                    },
                    "<NextNode>k__BackingField": {
                        "_value": "01d718d2-756a-4b95-8522-04b7e2ccadb0"
                    },
                    "<Text>k__BackingField": ""
                }
            },
            {
                "rid": 1004,
                "type": {
                    "class": "DialogueReplicaNodeData",
                    "ns": "KissMyAssets.VisualNovelCore.Runtime",
                    "asm": "Assembly-CSharp"
                },
                "data": {
                    "<NodeId>k__BackingField": {
                        "_value": "01d718d2-756a-4b95-8522-04b7e2ccadb0"
                    },
                    "<BackgroundHolder>k__BackingField": {
                        "<BackgroundId>k__BackingField": {
                            "_value": "00000000-0000-0000-0000-000000000000"
                        }
                    },
                    "<ActorsHolder>k__BackingField": {
                        "rid": 1008
                    },
                    "<Position>k__BackingField": {
                        "x": 520.4000244140625,
                        "y": 58.000022888183597
                    },
                    "<NextNode>k__BackingField": {
                        "_value": "06a71dd6-5d19-48d3-9b5e-635b7b6b6552"
                    },
                    "<Text>k__BackingField": ""
                }
            },
            {
                "rid": 1005,
                "type": {
                    "class": "DialogueReplicaNodeData",
                    "ns": "KissMyAssets.VisualNovelCore.Runtime",
                    "asm": "Assembly-CSharp"
                },
                "data": {
                    "<NodeId>k__BackingField": {
                        "_value": "06a71dd6-5d19-48d3-9b5e-635b7b6b6552"
                    },
                    "<BackgroundHolder>k__BackingField": {
                        "<BackgroundId>k__BackingField": {
                            "_value": "00000000-0000-0000-0000-000000000000"
                        }
                    },
                    "<ActorsHolder>k__BackingField": {
                        "rid": 1009
                    },
                    "<Position>k__BackingField": {
                        "x": 962.0,
                        "y": 91.60000610351563
                    },
                    "<NextNode>k__BackingField": {
                        "_value": "4c330dd9-3755-4e5b-a73b-1044234131b0"
                    },
                    "<Text>k__BackingField": ""
                }
            },
            {
                "rid": 1006,
                "type": {
                    "class": "ActorsHolderData",
                    "ns": "KissMyAssets.VisualNovelCore.Runtime",
                    "asm": "Assembly-CSharp"
                },
                "data": {
                    "<Actors>k__BackingField": []
                }
            },
            {
                "rid": 1007,
                "type": {
                    "class": "ActorsHolderData",
                    "ns": "KissMyAssets.VisualNovelCore.Runtime",
                    "asm": "Assembly-CSharp"
                },
                "data": {
                    "<Actors>k__BackingField": [
                        {
                            "rid": 1010
                        }
                    ]
                }
            },
            {
                "rid": 1008,
                "type": {
                    "class": "ActorsHolderData",
                    "ns": "KissMyAssets.VisualNovelCore.Runtime",
                    "asm": "Assembly-CSharp"
                },
                "data": {
                    "<Actors>k__BackingField": [
                        {
                            "rid": 1011
                        }
                    ]
                }
            },
            {
                "rid": 1009,
                "type": {
                    "class": "ActorsHolderData",
                    "ns": "KissMyAssets.VisualNovelCore.Runtime",
                    "asm": "Assembly-CSharp"
                },
                "data": {
                    "<Actors>k__BackingField": [
                        {
                            "rid": 1012
                        }
                    ]
                }
            },
            {
                "rid": 1010,
                "type": {
                    "class": "DialogueActorData",
                    "ns": "KissMyAssets.VisualNovelCore.Runtime",
                    "asm": "Assembly-CSharp"
                },
                "data": {
                    "<ActorDataId>k__BackingField": {
                        "_value": "ccbf9ae4-a2f4-43bc-b713-4ff815b878de"
                    },
                    "<Alignment>k__BackingField": 1,
                    "<ActorEmotion>k__BackingField": 0
                }
            },
            {
                "rid": 1011,
                "type": {
                    "class": "DialogueActorData",
                    "ns": "KissMyAssets.VisualNovelCore.Runtime",
                    "asm": "Assembly-CSharp"
                },
                "data": {
                    "<ActorDataId>k__BackingField": {
                        "_value": "ccbf9ae4-a2f4-43bc-b713-4ff815b878de"
                    },
                    "<Alignment>k__BackingField": 1,
                    "<ActorEmotion>k__BackingField": 0
                }
            },
            {
                "rid": 1012,
                "type": {
                    "class": "DialogueActorData",
                    "ns": "KissMyAssets.VisualNovelCore.Runtime",
                    "asm": "Assembly-CSharp"
                },
                "data": {
                    "<ActorDataId>k__BackingField": {
                        "_value": "ccbf9ae4-a2f4-43bc-b713-4ff815b878de"
                    },
                    "<Alignment>k__BackingField": 1,
                    "<ActorEmotion>k__BackingField": 0
                }
            }
        ]
    }
}